iching/__init__.py
iching/iching.py
iching/package_data.dat
iching/plot.py
iching-3.8.2.dist-info/licenses/LICENSE
sample/__init__.py
iching-3.8.2.dist-info/METADATA
iching-3.8.2.dist-info/WHEEL
iching-3.8.2.dist-info/top_level.txt
iching-3.8.2.dist-info/RECORD
