Metadata-Version: 2.4
Name: iching
Version: 3.8.2
Summary: Book of Changes
Home-page: https://github.com/chengjun/iching
Author: Cheng-Jun Wang
Author-email: Cheng-Jun Wang <wangchj04@gmail.com>
Project-URL: Homepage, https://github.com/chengjun/iching
Project-URL: Bug Tracker, https://github.com/chengjun/iching/issues
Classifier: Programming Language :: Python :: 3
Classifier: License :: OSI Approved :: MIT License
Classifier: Operating System :: OS Independent
Requires-Python: >=3.7
License-File: LICENSE
Dynamic: author
Dynamic: home-page
Dynamic: license-file
